LICENSE
MANIFEST.in
README
setup.py
dynamodb_config_store/__init__.py
dynamodb_config_store/exceptions.py
dynamodb_config_store/settings.conf
dynamodb_config_store.egg-info/PKG-INFO
dynamodb_config_store.egg-info/SOURCES.txt
dynamodb_config_store.egg-info/dependency_links.txt
dynamodb_config_store.egg-info/not-zip-safe
dynamodb_config_store.egg-info/requires.txt
dynamodb_config_store.egg-info/top_level.txt
dynamodb_config_store/config_stores/__init__.py
dynamodb_config_store/config_stores/simple.py
dynamodb_config_store/config_stores/time_based.py