Metadata-Version: 1.1
Name: dynamodb-config-store
Version: 0.3.0
Summary: Store configuration details in DynamoDB
Home-page: https://github.com/sebdah/dynamodb-config-store/
Author: Sebastian Dahlgren
Author-email: sebastian.dahlgren@gmail.com
License: Apache License, Version 2.0
Keywords: dynamodb aws config configuration amazon web services
Platform: Any
Classifier: Development Status :: 4 - Beta
Classifier: Environment :: Console
Classifier: License :: OSI Approved :: Apache Software License
Classifier: Operating System :: OS Independent
Classifier: Programming Language :: Python
